setup.py
genderdecoder/__init__.py
genderdecoder/assess.py
genderdecoder/wordlists.py
genderdecoder.egg-info/PKG-INFO
genderdecoder.egg-info/SOURCES.txt
genderdecoder.egg-info/dependency_links.txt
genderdecoder.egg-info/not-zip-safe
genderdecoder.egg-info/top_level.txt