Metadata-Version: 1.0
Name: genderdecoder
Version: 0.3
Summary: Check for gender-coded words in job adverts. A package of the service provided at http://gender-decoder.katmatfield.com
Home-page: http://github.com/Doteveryone/genderdecoder
Author: Doteveryone
Author-email: admin@doteveryone.org.uk
License: MIT
Platform: UNKNOWN
